typed_data_structures/Heap.py
typed_data_structures/Queue.py
typed_data_structures/Stack.py
typed_data_structures/__init__.py
typed_data_structures/__version__.py
typed_data_structures-0.0.2.dist-info/METADATA
typed_data_structures-0.0.2.dist-info/WHEEL
typed_data_structures-0.0.2.dist-info/top_level.txt
typed_data_structures-0.0.2.dist-info/RECORD
